codi_payrolldates/__init__.py
codi_payrolldates/calc.py
codi_payrolldates-0.3.0.dist-info/WHEEL
codi_payrolldates-0.3.0.dist-info/METADATA
codi_payrolldates-0.3.0.dist-info/RECORD
