Metadata-Version: 2.1
Name: codi_payrolldates
Version: 0.3.0
Summary: Python library for getting payroll dates
Author: Jesse Clark
Requires-Python: >=3.9
Classifier: Development Status :: 3 - Alpha
Classifier: Intended Audience :: Developers
Classifier: License :: OSI Approved :: MIT License
Classifier: Programming Language :: Python :: 3.9
Classifier: Programming Language :: Python :: 3.10
Classifier: Programming Language :: Python :: 3.11
Requires-Dist: flit ; extra == "dev"
Requires-Dist: sphinx ; extra == "doc"
Provides-Extra: dev
Provides-Extra: doc
